{
  "SSS-0001": {
    "tracking_number": "SSS-0001",
    "asset_description": "Gold Bullion - 12kg",
    "shipment_status": "In Transit",
    "customs_status": "Cleared",
    "duties_taxes": "$0",
    "insurance_status": "Insured",
    "security_level": "High",
    "receiver_status": "Pending",
    "last_location": "Heathrow Airport",
    "customs_agent": "Agent V",
    "agent_id": "AG-101",
    "notice_text": "Handle in secure room. GPS custody active.",
    "shipment_date": "2026-06-01",
    "expected_date": "2026-06-10",
    "latitude": 51.47,
    "longitude": -0.4543,
    "city": "Hounslow, UK",
    "route_index": 0,
    "airway_bill": "112-576488934",
    "flight_no": "SS00324",
    "total_freight": "120kg",
    "total_value": "£20,375",
    "handling_fee": "Unpaid",
    "delivery_type": "Economy",
    "delivery_address": "170 Deville Hill Road, 71342 Jena, LA",
    "origin": "Heathrow Airport",
    "destination": "Charlotte Douglas International Airport",
    "route": [
      {"lat": 51.47, "lng": -0.4543, "city": "Hounslow, UK", "last_location": "Heathrow Airport"},
      {"lat": 35.214, "lng": -80.9431, "city": "Charlotte, NC, USA", "last_location": "Charlotte Douglas International Airport"}
    ],
    "last_updated": "2026-06-27 01:24:35"
  },
  "SSS-0002": {
    "tracking_number": "SSS-0002",
    "asset_description": "Diamond Shipment - Box A",
    "shipment_status": "Delivered",
    "customs_status": "Cleared",
    "duties_taxes": "$0",
    "insurance_status": "Claimed",
    "security_level": "Top",
    "receiver_status": "Signed",
    "last_location": "Zurich Vault Facility",
    "customs_agent": "Agent Z",
    "agent_id": "AG-202",
    "notice_text": "",
    "shipment_date": "2026-05-20",
    "expected_date": "2026-05-22",
    "latitude": 47.3769,
    "longitude": 8.5417,
    "city": "Zurich, Switzerland",
    "route_index": 0,
    "route": [],
    "airway_bill": "112-576488934",
    "flight_no": "SS00324",
    "total_freight": "120kg",
    "total_value": "£20,375",
    "handling_fee": "Unpaid",
    "delivery_type": "Economy",
    "delivery_address": "170 Deville Hill Road, 71342 Jena, LA",
    "origin": "Heathrow Airport",
    "destination": "Charlotte Douglas International Airport",
    "last_updated": "2026-06-27 01:24:35"
  },
  "GBX-2026-458721": {
    "tracking_number": "GBX-2026-458721",
    "asset_description": "Secure Vault Transfer - Sovereign Cargo",
    "shipment_status": "In Transit",
    "customs_status": "Awaiting Clearance",
    "duties_taxes": "$18,900",
    "insurance_status": "Insured",
    "security_level": "Critical",
    "receiver_status": "Pending",
    "last_location": "Heathrow Airport",
    "customs_agent": "Agent K",
    "agent_id": "AG-421",
    "notice_text": "Custom Interceptions for tax inspection",
    "shipment_date": "2026-06-02",
    "expected_date": "2026-06-12",
    "latitude": 51.47,
    "longitude": -0.4543,
    "city": "Hounslow, UK",
    "route_index": 0,
    "airway_bill": "112-576488934",
    "flight_no": "SS00324",
    "total_freight": "120kg",
    "total_value": "£20,375",
    "handling_fee": "Unpaid",
    "delivery_type": "Economy",
    "delivery_address": "170 Deville Hill Road, 71342 Jena, LA",
    "origin": "Heathrow Airport",
    "destination": "Charlotte Douglas International Airport",
    "route": [
      {"lat": 51.47, "lng": -0.4543, "city": "Hounslow, UK", "last_location": "Heathrow Airport"},
      {"lat": 35.214, "lng": -80.9431, "city": "Charlotte, NC, USA", "last_location": "Charlotte Douglas International Airport"}
    ],
    "last_updated": "2026-06-27 03:01:24"
  }
}
